{
  "generated_at": "2026-07-21T17:00:25.357484+00:00",
  "leagues": {
    "liga-arg": {
      "results": [],
      "next": [
        {
          "home": "30\nSarmiento",
          "away": "Argentinos",
          "meta": "próximo · 16:30"
        },
        {
          "home": "Belgrano",
          "away": "Central",
          "meta": "próximo · 18:45"
        },
        {
          "home": "00\nRacing",
          "away": "Gimnasia",
          "meta": "próximo · 16:00"
        },
        {
          "home": "Vélez",
          "away": "Instituto",
          "meta": "próximo · 18:15"
        },
        {
          "home": "Platense",
          "away": "Unión",
          "meta": "próximo · 18:15"
        },
        {
          "home": "45\nEstudiantes RC",
          "away": "Tigre",
          "meta": "próximo · 14:00"
        },
        {
          "home": "Newell's",
          "away": "Talleres",
          "meta": "próximo · 16:15"
        },
        {
          "home": "River",
          "away": "Barracas",
          "meta": "próximo · 18:30"
        },
        {
          "home": "00\nAtl. Tucumán",
          "away": "Independiente Riv.",
          "meta": "próximo · 14:15"
        },
        {
          "home": "Estudiantes",
          "away": "Independiente",
          "meta": "próximo · 16:30"
        }
      ]
    },
    "nacional": {
      "results": [],
      "next": [
        {
          "home": "00\nEstudiantes",
          "away": "Bolivar",
          "meta": "próximo · 13:00"
        },
        {
          "home": "Atlético Rafaela",
          "away": "Chicago",
          "meta": "próximo · 16:00"
        },
        {
          "home": "00\nMorón",
          "away": "Ferro",
          "meta": "próximo · 12:00"
        },
        {
          "home": "Los Andes",
          "away": "Dep. Madryn",
          "meta": "próximo · 12:00"
        },
        {
          "home": "All Boys",
          "away": "Defensores",
          "meta": "próximo · 12:00"
        },
        {
          "home": "Tristan Suárez",
          "away": "Chacarita",
          "meta": "próximo · 12:00"
        },
        {
          "home": "Agropecuario",
          "away": "San Martín",
          "meta": "próximo · 12:30"
        },
        {
          "home": "San Miguel",
          "away": "Acassuso",
          "meta": "próximo · 12:30"
        },
        {
          "home": "Colón",
          "away": "Chaco For Ever",
          "meta": "próximo · 13:00"
        },
        {
          "home": "00\nCA Mitre",
          "away": "Alte. Brown",
          "meta": "próximo · 13:00"
        }
      ]
    },
    "metro": {
      "results": [],
      "next": [
        {
          "home": "00\nLaferrere",
          "away": "Talleres RE",
          "meta": "próximo · 11:00"
        },
        {
          "home": "00\nArmenio",
          "away": "Arsenal",
          "meta": "próximo · 11:00"
        },
        {
          "home": "Flandria",
          "away": "Excursionistas",
          "meta": "próximo · 11:00"
        },
        {
          "home": "00\nCADU",
          "away": "UAI Urquiza",
          "meta": "próximo · 11:00"
        },
        {
          "home": "Dock Sud",
          "away": "Liniers",
          "meta": "próximo · 11:00"
        },
        {
          "home": "Comunicaciones",
          "away": "Real Pilar",
          "meta": "próximo · 11:00"
        },
        {
          "home": "Merlo",
          "away": "San Carlos",
          "meta": "próximo · 11:00"
        }
      ]
    },
    "primerac": {
      "results": [],
      "next": [
        {
          "home": "00\nBerazategui",
          "away": "Mercedes",
          "meta": "próximo · 12:00"
        },
        {
          "home": "Cañuelas",
          "away": "Muñiz",
          "meta": "próximo · 12:00"
        },
        {
          "home": "CA Atlas",
          "away": "Dep. Español",
          "meta": "próximo · 12:00"
        },
        {
          "home": "Argentino Rosario",
          "away": "Puerto Nuevo",
          "meta": "próximo · 12:00"
        },
        {
          "home": "Estrella del Sur",
          "away": "Paraguayo",
          "meta": "próximo · 12:00"
        },
        {
          "home": "Victoriano",
          "away": "JJ Urquiza",
          "meta": "próximo · 12:00"
        },
        {
          "home": "CA Lugano",
          "away": "Centro Español",
          "meta": "próximo · 12:00"
        },
        {
          "home": "00\nLamadrid",
          "away": "Claypole",
          "meta": "próximo · 12:00"
        },
        {
          "home": "Luján",
          "away": "Central Ballester",
          "meta": "próximo · 12:00"
        },
        {
          "home": "Sp. Barracas",
          "away": "El Porvenir",
          "meta": "próximo · 12:00"
        }
      ]
    }
  }
}